structmlib/__init__.py
structmlib/core.py
structmlib-0.1.1.dist-info/licenses/LICENSE
structmlib-0.1.1.dist-info/METADATA
structmlib-0.1.1.dist-info/WHEEL
structmlib-0.1.1.dist-info/top_level.txt
structmlib-0.1.1.dist-info/RECORD
