Metadata-Version: 2.4
Name: structmlib
Version: 0.1.1
Summary: A framework for structural engineering machine learning
Author-email: Carlos Couto <ccouto@ua.pt>
License: MIT License
Keywords: structural engineering,machine learning,python
Classifier: Programming Language :: Python :: 3
Classifier: License :: OSI Approved :: MIT License
Classifier: Operating System :: OS Independent
Requires-Python: >=3.8
License-File: LICENSE
Requires-Dist: numpy
Requires-Dist: pandas
Requires-Dist: scikit-learn
Dynamic: license-file
